dar_invenio_cli/__init__.py
dar_invenio_cli/cli.py
dar_invenio_cli/config.py
dar_invenio_cli/core.py
dar_invenio_cli/tools.py
dar_invenio_cli/services/__init__.py
dar_invenio_cli/services/file_service.py
dar_invenio_cli/test_data/__init__.py
dar_invenio_cli/uploaders/__init__.py
dar_invenio_cli/uploaders/base_uploader.py
dar_invenio_cli/uploaders/file_uploader.py
dar_invenio_cli/uploaders/multipart_uploader.py
dar_invenio_cli-0.2.7.dist-info/licenses/AUTHORS.rst
dar_invenio_cli-0.2.7.dist-info/licenses/LICENSE
dar_invenio_cli-0.2.7.dist-info/METADATA
dar_invenio_cli-0.2.7.dist-info/WHEEL
dar_invenio_cli-0.2.7.dist-info/entry_points.txt
dar_invenio_cli-0.2.7.dist-info/top_level.txt
dar_invenio_cli-0.2.7.dist-info/RECORD
