Metadata-Version: 2.4
Name: dar_invenio_cli
Version: 0.2.7
Summary: Dar Invenio Command Line Interface
Home-page: https://gitlab.ics.muni.cz/dataraptors/elter/dar-invenio-cli
Author: Dominik Dubovsky <485020@mail.muni.cz>
License: MIT
Project-URL: Source, https://gitlab.ics.muni.cz/dataraptors/elter/dar-invenio-cli
Requires-Python: >=3.10
License-File: LICENSE
License-File: AUTHORS.rst
Requires-Dist: requests
Requires-Dist: asyncio
Requires-Dist: aiohttp
Requires-Dist: click
Dynamic: license-file
